MANIFEST.in
README.rst
setup.py
django_social_poster.egg-info/PKG-INFO
django_social_poster.egg-info/SOURCES.txt
django_social_poster.egg-info/dependency_links.txt
django_social_poster.egg-info/not-zip-safe
django_social_poster.egg-info/requires.txt
django_social_poster.egg-info/top_level.txt
social_poster/__init__.py
social_poster/models.py
social_poster/signals.py
social_poster/locale/de/LC_MESSAGES/django.mo
social_poster/locale/de/LC_MESSAGES/django.po