Metadata-Version: 1.0
Name: django-social-poster
Version: 0.1
Summary: Signals for posting messages on Facebook and Twitter.
Home-page: https://github.com/raphaa/django-social-poster
Author: Raphael Jasjukaitis
Author-email: webmaster@raphaa.de
License: BSD License
Platform: OS Independent
Classifier: Environment :: Web Environment
Classifier: License :: OSI Approved :: BSD License
Classifier: Operating System :: OS Independent
Classifier: Programming Language :: Python
Classifier: Framework :: Django
